lightning_mcp/__init__.py
lightning_mcp/cli.py
lightning_mcp/constants.py
lightning_mcp/http_server.py
lightning_mcp/protocol.py
lightning_mcp/server.py
lightning_mcp/tools.py
lightning_mcp/handlers/__init__.py
lightning_mcp/handlers/base.py
lightning_mcp/handlers/checkpoint.py
lightning_mcp/handlers/inspect.py
lightning_mcp/handlers/predict.py
lightning_mcp/handlers/test.py
lightning_mcp/handlers/train.py
lightning_mcp/handlers/validate.py
lightning_mcp/lightning/__init__.py
lightning_mcp/lightning/trainer.py
lightning_mcp/models/__init__.py
lightning_mcp/models/simple.py
lightning_mcp-0.5.0.dist-info/METADATA
lightning_mcp-0.5.0.dist-info/WHEEL
lightning_mcp-0.5.0.dist-info/entry_points.txt
lightning_mcp-0.5.0.dist-info/licenses/LICENSE
lightning_mcp-0.5.0.dist-info/RECORD
