Metadata-Version: 2.4
Name: lightning-mcp
Version: 0.5.0
Summary: Model Context Protocol (MCP) server for PyTorch Lightning
Author: Pratyush Mishra
License: Apache-2.0
License-File: LICENSE
Requires-Python: <3.13,>=3.10
Requires-Dist: pydantic>=2.6
Requires-Dist: pytorch-lightning>=2.2
Requires-Dist: torch>=2.1
Provides-Extra: dev
Requires-Dist: fastapi>=0.110; extra == 'dev'
Requires-Dist: httpx>=0.25; extra == 'dev'
Requires-Dist: mypy>=1.7; extra == 'dev'
Requires-Dist: pre-commit>=3.5; extra == 'dev'
Requires-Dist: pytest-cov; extra == 'dev'
Requires-Dist: pytest>=8.0; extra == 'dev'
Requires-Dist: ruff>=0.1.13; extra == 'dev'
Requires-Dist: uvicorn>=0.29; extra == 'dev'
Provides-Extra: server
Requires-Dist: fastapi>=0.110; extra == 'server'
Requires-Dist: uvicorn>=0.29; extra == 'server'
